nucad/__init__.py
nucad/core/__init__.py
nucad/core/api.py
nucad/core/geometry.py
nucad/core/material.py
nucad/core/particle.py
nucad/core/track.py
nucad/core/util.py
nucad/error.py
nucad/physics/__init__.py
nucad/physics/relkin.py
nucad/setup/__init__.py
nucad/setup/setup.py
nucad/types.py
nucad-0.1.0a4.dist-info/WHEEL
nucad-0.1.0a4.dist-info/METADATA
nucad-0.1.0a4.dist-info/RECORD
