Metadata-Version: 2.3
Name: nucad
Version: 0.1.0a4
Summary: CAD tool focused on designing nuclear physics experimental instruments
Author: Takayuki Yano
Author-email: Takayuki Yano <yano.takayuki.55w@st.kyoto-u.ac.jp>
Requires-Dist: cadquery>=2.5.2
Requires-Dist: numpy>=2.0.0
Requires-Dist: pycatima>=1.98
Requires-Python: >=3.11
Project-URL: source, https://github.com/yano404/NuCAD
